dp/__init__.py
dp/__main__.py
dp/annotations.py
dp/auth.py
dp/config.py
dp/lab.py
dp/main.py
dp/py.typed
dp/team_api.py
dp/utils.py
dapla_cli-0.3.0.dist-info/LICENSE
dapla_cli-0.3.0.dist-info/METADATA
dapla_cli-0.3.0.dist-info/WHEEL
dapla_cli-0.3.0.dist-info/entry_points.txt
dapla_cli-0.3.0.dist-info/RECORD
