Metadata-Version: 2.1
Name: dapla-cli
Version: 0.3.0
Summary: Dapla CLI
Home-page: https://github.com/statisticsnorway/dapla-cli
License: MIT
Author: Team Statistikktjenester
Requires-Python: >=3.12
Classifier: Development Status :: 4 - Beta
Classifier: License :: OSI Approved :: MIT License
Classifier: Programming Language :: Python :: 3
Classifier: Programming Language :: Python :: 3.12
Classifier: Programming Language :: Python :: 3.13
Requires-Dist: click (>=8.0.1)
Requires-Dist: pydantic (>=2.9.2,<3.0.0)
Requires-Dist: pyjwt (>=2.9.0,<3.0.0)
Requires-Dist: pyperclip (>=1.9.0,<2.0.0)
Requires-Dist: pytest-mock (>=3.14.0,<4.0.0)
Requires-Dist: python-dateutil (>=2.9.0.post0,<3.0.0)
Requires-Dist: requests (>=2.32.3,<3.0.0)
Requires-Dist: typer (>=0.12.5)
Requires-Dist: types-requests (>=2.32.0.20240907,<3.0.0.0)
Project-URL: Changelog, https://github.com/statisticsnorway/dapla-cli/releases
Project-URL: Documentation, https://statisticsnorway.github.io/dapla-cli
Project-URL: Repository, https://github.com/statisticsnorway/dapla-cli
